main.py
config/__init__.py
config/config_loader.py
config/exceptions.py
core/entities/__init__.py
core/entities/malicious_package.py
core/entities/notification_event.py
core/entities/registry_package_match.py
core/entities/scan_result.py
core/interfaces/__init__.py
core/interfaces/notification_service.py
core/interfaces/packages_feed.py
core/interfaces/packages_registry_service.py
core/interfaces/storage_service.py
core/usecases/__init__.py
core/usecases/configuration_management.py
core/usecases/data_management.py
core/usecases/feed_management.py
core/usecases/health_management.py
core/usecases/notification_testing.py
core/usecases/package_management.py
core/usecases/proactive_security.py
core/usecases/registry_management.py
core/usecases/scan_results.py
core/usecases/security_analysis.py
core/usecases/security_scanner.py
core/usecases/test_data_management.py
core/utils/__init__.py
core/utils/version_matcher.py
factories/__init__.py
factories/service_factory.py
malifiscan-1.0.0.dist-info/licenses/LICENSE.md
providers/exceptions.py
providers/feeds/__init__.py
providers/feeds/memory_feed.py
providers/feeds/osv_feed.py
providers/notifications/__init__.py
providers/notifications/composite_notifier.py
providers/notifications/msteams_notifier.py
providers/notifications/null_notifier.py
providers/notifications/webhook_notifier.py
providers/registries/__init__.py
providers/registries/jfrog_registry.py
providers/registries/null_registry.py
providers/storage/__init__.py
providers/storage/database_storage.py
providers/storage/file_storage.py
providers/storage/memory_storage.py
malifiscan-1.0.0.dist-info/METADATA
malifiscan-1.0.0.dist-info/WHEEL
malifiscan-1.0.0.dist-info/entry_points.txt
malifiscan-1.0.0.dist-info/top_level.txt
malifiscan-1.0.0.dist-info/RECORD
