Metadata-Version: 2.4
Name: malifiscan
Version: 1.0.0
Summary: A security tool that detects malicious packages from external vulnerability feeds and searches for them in your package registries or artifact repositories.
Author-email: Security Team <security@example.com>
License: MIT
Classifier: Development Status :: 4 - Beta
Classifier: Intended Audience :: Developers
Classifier: License :: OSI Approved :: MIT License
Classifier: Operating System :: OS Independent
Classifier: Programming Language :: Python :: 3
Classifier: Programming Language :: Python :: 3.9
Classifier: Programming Language :: Python :: 3.10
Classifier: Programming Language :: Python :: 3.11
Classifier: Programming Language :: Python :: 3.12
Classifier: Programming Language :: Python :: 3.13
Requires-Python: >=3.9
License-File: LICENSE.md
Requires-Dist: aiofiles==24.1.0
Requires-Dist: aiohttp==3.9.1
Requires-Dist: aiosqlite==0.21.0
Requires-Dist: google-cloud-storage>=3.4.0
Requires-Dist: protobuf==6.32.1
Requires-Dist: pydantic==1.10.12
Requires-Dist: python-dotenv==1.1.1
Requires-Dist: PyYAML==6.0.2
Requires-Dist: rich==14.1.0
Requires-Dist: sqlalchemy>=1.4.0
Provides-Extra: test
Requires-Dist: pytest==7.4.3; extra == "test"
Requires-Dist: pytest-asyncio==0.21.1; extra == "test"
Requires-Dist: pytest-cov>=4.0.0; extra == "test"
Provides-Extra: dev
Requires-Dist: pytest==7.4.3; extra == "dev"
Requires-Dist: pytest-asyncio==0.21.1; extra == "dev"
Requires-Dist: pytest-cov>=4.0.0; extra == "dev"
Requires-Dist: black>=23.0.0; extra == "dev"
Requires-Dist: isort>=5.12.0; extra == "dev"
Requires-Dist: flake8>=6.0.0; extra == "dev"
Requires-Dist: pre-commit>=4.3.0; extra == "dev"
Dynamic: license-file
